maswavespy-1.0.1.dist-info/WHEEL
maswavespy-1.0.1.dist-info/top_level.txt
maswavespy-1.0.1.dist-info/RECORD
maswavespy-1.0.1.dist-info/LICENSE
maswavespy-1.0.1.dist-info/METADATA
maswavespy/wavefield.py
maswavespy/cy_theoretical_dc.pyx
maswavespy/cy_theoretical_dc.cpython-311-x86_64-linux-gnu.so
maswavespy/select_dc.py
maswavespy/cy_dispersion_imaging.cpython-311-x86_64-linux-gnu.so
maswavespy/cy_dispersion_imaging.cpp
maswavespy/cy_dispersion_imaging.pyx
maswavespy/combination.py
maswavespy/dispersion.py
maswavespy/dataset.py
maswavespy/cy_theoretical_dc.cpp
maswavespy/__init__.py
maswavespy/supplemental.py
maswavespy/inversion.py
