Metadata-Version: 2.1
Name: maswavespy
Version: 1.0.1
Summary: MASWavesPy, a Python package for processing and inverting MASW data
Author-email: Elin Asta Olafsdottir <elinasta@hi.is>
Project-URL: Homepage, https://github.com/Mazvel/maswavespy
Project-URL: Bug Tracker, https://github.com/Mazvel/maswavespy/issues
Classifier: Programming Language :: Python :: 3
Classifier: License :: OSI Approved :: MIT License
Classifier: Operating System :: OS Independent
Requires-Python: >=3.7
License-File: LICENSE
Requires-Dist: build <2,>=1.0
Requires-Dist: certifi
Requires-Dist: charset-normalizer
Requires-Dist: contourpy
Requires-Dist: cycler
Requires-Dist: Cython <4,>=3.0
Requires-Dist: decorator
Requires-Dist: fonttools
Requires-Dist: idna
Requires-Dist: kiwisolver
Requires-Dist: lxml
Requires-Dist: matplotlib <4,>=3.5
Requires-Dist: numpy <2,>=1.0
Requires-Dist: obspy
Requires-Dist: packaging
Requires-Dist: pandas <3,>=2.0
Requires-Dist: Pillow
Requires-Dist: pyparsing
Requires-Dist: pyproject-hooks
Requires-Dist: python-dateutil
Requires-Dist: pytz
Requires-Dist: requests
Requires-Dist: scipy <2,>=1.0
Requires-Dist: six
Requires-Dist: SQLAlchemy
Requires-Dist: tk
Requires-Dist: typing-extensions
Requires-Dist: tzdata
Requires-Dist: urllib3
Provides-Extra: test
Requires-Dist: pytest ; extra == 'test'
Requires-Dist: pytest-cov ; extra == 'test'
